mostoop
