Metadata-Version: 1.1
Name: mostoop
Version: 0.0.3
Summary: OOP Learning by Most
Home-page: https://github.com/Thanapat-most/OOP-learning
Author: Thanapat-most
Author-email: thanapat.most2543@gmail.com
License: MIT
Download-URL: https://github.com/Thanapat-most/OOP-learning/archive/v0.0.3.zip
Keywords: OOP,most,learning
Platform: UNKNOWN
Classifier: Development Status :: 3 - Alpha
Classifier: Intended Audience :: Education
Classifier: Topic :: Software Development :: Build Tools
Classifier: License :: OSI Approved :: MIT License
Classifier: Programming Language :: Python :: 3
Classifier: Programming Language :: Python :: 3.4
Classifier: Programming Language :: Python :: 3.5
Classifier: Programming Language :: Python :: 3.6
Classifier: Programming Language :: Python :: 3.7
Classifier: Programming Language :: Python :: 3.8
Classifier: Programming Language :: Python :: 3.9
